TEXTFUN/_init_.py
TEXTFUN/funciones.py
pruebadanielvega-0.0.3.dist-info/METADATA
pruebadanielvega-0.0.3.dist-info/WHEEL
pruebadanielvega-0.0.3.dist-info/top_level.txt
pruebadanielvega-0.0.3.dist-info/RECORD
