Metadata-Version: 2.4
Name: pruebaDanielVega
Version: 0.0.3
Summary: Librería 
Author: Daniel Vega
Requires-Python: >=3.8
